{"title":"San Francisco/Chinatown-North Beach","name":"Cafe Zoetrope","alt":null,"address":"916 Kearny St","directions":"at Columbus","phone":"+1 415 291-1700","tollfree":null,"email":null,"url":"http://www.cafecoppola.com/cafezoetrope//","hours":"M-F 11AM-10PM, Sa Noon-10, Su Noon-9","image":null,"price":null,"content":"Owned by the film director Francis Ford Coppola, Zoetrope is an elegant Italian restaurant located in a historic landmark, the Sentinel Building, in the shadow of the Transamerica Pyramid.","geo":{"lat":37.7965,"lon":-122.405,"accuracy":"RANGE_INTERPOLATED"},"activity":"eat","type":"landmark","id":25451,"country":"United States","city":"San Francisco","state":"California"}