{"title":"Liverpool","name":"St. George's Hall","alt":null,"address":"Lime St","directions":"near railway station","phone":null,"tollfree":null,"email":null,"url":null,"hours":null,"image":null,"price":"Free","content":"A mammoth of a Greco-Roman-style building which was built by wealthy merchants for the people of the city. It is arguably the finest neo-classical building in Western Europe, and has recently been thoroughly restored for Capital of Culture Year. Inside it has one of the best church organs in Europe. On the outside it has a selection of classical murals which were thought quite shocking in their day (due to the shameful female nudity).","geo":{"lat":53.40867,"lon":-2.98017,"accuracy":"APPROXIMATE"},"activity":"see","type":"landmark","id":15849,"country":"United Kingdom","city":"Liverpool","state":null}