{"title":"Santa Monica Mountains National Recreation Area","name":"Malibu Creek State Park","alt":null,"address":"1925 Las Virgenes Road, Calabasas, CA 91302","directions":null,"phone":"+1 818 880-0367","tollfree":null,"email":null,"url":"http://www.parks.ca.gov/?page_id=614","hours":"Dawn-Dusk","image":null,"price":"Parking $12, free with state park pass","content":"Made up of land once owned by Bob Hope, Ronald Reagan, and 20th Century Fox, this park was used for the filming of many famous movies and TV shows, including the 1960s classics &quot;Doctor Dolitte&quot; and &quot;Planet of the Apes&quot; and the 1970s-80s TV series &quot;M*A*S*H&quot;. A trail that leads along Malibu Creek brings hikers to the '''Rock Pool''', a swimming and diving spot which is surrounded by high cliffs popular with rock climbers, scenic '''Century Lake''', and the remains of the &quot;M*A*S*H&quot; set, which were badly damaged by a wildfire but still contains a few relics. Horseback riding, mountain biking, and camping are popular activities here. Rangers are on staff during the weekends to answer questions and help you find your way around.","geo":{"lat":34.10081,"lon":-118.711134,"accuracy":"RANGE_INTERPOLATED"},"activity":"see","type":"landmark","id":37581,"country":"United States","city":"Agoura Hills","state":"California"}