{"title":"London/Westminster","name":"Quaglinos","alt":null,"address":"16 Bury St, SW1Y 6AJ","directions":"tube: Green Park","phone":"+44 20 7930-6767","tollfree":null,"email":null,"url":null,"hours":null,"image":null,"price":null,"content":"Owned by famed designer Terence Conrad, it serves standard food with a menu that changes frequently. It features live jazz every night and on Sunday lunch.","geo":{"lat":51.5074,"lon":-0.1389,"accuracy":"ROOFTOP"},"activity":"eat","type":"landmark","id":16501,"country":"United Kingdom","city":"London","state":null}