{"title":"Los Angeles/Downtown","name":"Chinatown","alt":null,"address":null,"directions":null,"phone":null,"tollfree":null,"email":null,"url":"http://www.chinatownla.com","hours":null,"image":null,"price":null,"content":"Primarily centered around North Broadway; unlike Chinatowns in many other cities, it has a wide, main, busy street filled with small shops and restaurants. At about the middle point of N Broadway in Chinatown is an ''open market'' much like those found in [[Hong Kong]]. Be sure to [[haggle]]!","geo":{"lat":34.062384,"lon":-118.238322,"accuracy":"ROOFTOP"},"activity":"see","type":"landmark","id":16564,"country":"United States","city":"Los Angeles","state":"California"}