{"id":30424,"type":"route","airline":"GS","airlineid":"airline_690","sourceairport":"TSN","destinationairport":"SHE","stops":0,"equipment":"E90","schedule":[{"day":0,"utc":"14:24:00","flight":"GS345"},{"day":1,"utc":"00:09:00","flight":"GS129"},{"day":2,"utc":"11:38:00","flight":"GS867"},{"day":2,"utc":"02:21:00","flight":"GS428"},{"day":2,"utc":"07:07:00","flight":"GS770"},{"day":2,"utc":"13:37:00","flight":"GS157"},{"day":2,"utc":"12:49:00","flight":"GS458"},{"day":3,"utc":"01:49:00","flight":"GS092"},{"day":3,"utc":"00:55:00","flight":"GS960"},{"day":4,"utc":"17:00:00","flight":"GS750"},{"day":4,"utc":"10:07:00","flight":"GS573"},{"day":5,"utc":"09:36:00","flight":"GS670"},{"day":5,"utc":"05:51:00","flight":"GS203"},{"day":5,"utc":"18:37:00","flight":"GS777"},{"day":6,"utc":"22:13:00","flight":"GS333"},{"day":6,"utc":"05:20:00","flight":"GS717"},{"day":6,"utc":"10:47:00","flight":"GS631"},{"day":6,"utc":"21:51:00","flight":"GS245"}],"distance":563.2796696650391}