{"id":39464,"type":"route","airline":"LS","airlineid":"airline_3026","sourceairport":"NCL","destinationairport":"RHO","stops":0,"equipment":"752","schedule":[{"day":0,"utc":"18:18:00","flight":"LS091"},{"day":1,"utc":"18:05:00","flight":"LS777"},{"day":1,"utc":"00:55:00","flight":"LS798"},{"day":1,"utc":"16:05:00","flight":"LS697"},{"day":1,"utc":"21:35:00","flight":"LS261"},{"day":2,"utc":"09:38:00","flight":"LS795"},{"day":3,"utc":"20:25:00","flight":"LS422"},{"day":3,"utc":"21:12:00","flight":"LS099"},{"day":4,"utc":"16:28:00","flight":"LS828"},{"day":4,"utc":"22:14:00","flight":"LS499"},{"day":4,"utc":"09:55:00","flight":"LS963"},{"day":5,"utc":"21:23:00","flight":"LS693"},{"day":5,"utc":"16:35:00","flight":"LS934"},{"day":5,"utc":"02:47:00","flight":"LS360"},{"day":5,"utc":"01:13:00","flight":"LS500"},{"day":6,"utc":"00:29:00","flight":"LS633"},{"day":6,"utc":"22:09:00","flight":"LS752"},{"day":6,"utc":"00:53:00","flight":"LS858"},{"day":6,"utc":"00:28:00","flight":"LS820"}],"distance":3062.2695182879047}