{"id":21056,"type":"route","airline":"DL","airlineid":"airline_2009","sourceairport":"LAX","destinationairport":"HND","stops":0,"equipment":"76W","schedule":[{"day":0,"utc":"21:04:00","flight":"DL726"},{"day":0,"utc":"12:36:00","flight":"DL705"},{"day":0,"utc":"21:10:00","flight":"DL255"},{"day":1,"utc":"11:46:00","flight":"DL532"},{"day":1,"utc":"17:22:00","flight":"DL500"},{"day":2,"utc":"10:58:00","flight":"DL598"},{"day":2,"utc":"04:35:00","flight":"DL252"},{"day":2,"utc":"08:49:00","flight":"DL308"},{"day":2,"utc":"15:33:00","flight":"DL687"},{"day":2,"utc":"11:23:00","flight":"DL534"},{"day":3,"utc":"09:51:00","flight":"DL327"},{"day":4,"utc":"12:25:00","flight":"DL690"},{"day":5,"utc":"21:56:00","flight":"DL286"},{"day":5,"utc":"05:23:00","flight":"DL396"},{"day":6,"utc":"13:32:00","flight":"DL378"},{"day":6,"utc":"20:45:00","flight":"DL754"},{"day":6,"utc":"05:46:00","flight":"DL288"},{"day":6,"utc":"14:53:00","flight":"DL439"}],"distance":8812.412083321775}