{"id":20501,"type":"route","airline":"DL","airlineid":"airline_2009","sourceairport":"CVG","destinationairport":"MCO","stops":0,"equipment":"M88 320","schedule":[{"day":0,"utc":"09:33:00","flight":"DL047"},{"day":0,"utc":"00:15:00","flight":"DL069"},{"day":0,"utc":"14:05:00","flight":"DL848"},{"day":0,"utc":"12:42:00","flight":"DL163"},{"day":0,"utc":"18:00:00","flight":"DL018"},{"day":1,"utc":"15:01:00","flight":"DL971"},{"day":1,"utc":"05:02:00","flight":"DL994"},{"day":1,"utc":"00:40:00","flight":"DL189"},{"day":1,"utc":"23:12:00","flight":"DL940"},{"day":2,"utc":"08:49:00","flight":"DL775"},{"day":2,"utc":"01:12:00","flight":"DL072"},{"day":2,"utc":"01:40:00","flight":"DL323"},{"day":3,"utc":"20:13:00","flight":"DL040"},{"day":3,"utc":"18:52:00","flight":"DL042"},{"day":3,"utc":"09:27:00","flight":"DL965"},{"day":3,"utc":"05:58:00","flight":"DL345"},{"day":4,"utc":"21:46:00","flight":"DL578"},{"day":4,"utc":"21:45:00","flight":"DL883"},{"day":4,"utc":"00:33:00","flight":"DL206"},{"day":4,"utc":"09:58:00","flight":"DL272"},{"day":4,"utc":"21:08:00","flight":"DL687"},{"day":5,"utc":"16:58:00","flight":"DL327"},{"day":6,"utc":"19:04:00","flight":"DL957"}],"distance":1220.7209969697533}