{"id":22629,"type":"route","airline":"DY","airlineid":"airline_3737","sourceairport":"OSL","destinationairport":"MAN","stops":0,"equipment":"73H","schedule":[{"day":0,"utc":"13:56:00","flight":"DY135"},{"day":0,"utc":"19:49:00","flight":"DY443"},{"day":0,"utc":"18:32:00","flight":"DY316"},{"day":1,"utc":"07:21:00","flight":"DY810"},{"day":2,"utc":"01:25:00","flight":"DY457"},{"day":2,"utc":"14:24:00","flight":"DY126"},{"day":2,"utc":"16:00:00","flight":"DY973"},{"day":3,"utc":"06:12:00","flight":"DY944"},{"day":3,"utc":"16:00:00","flight":"DY111"},{"day":3,"utc":"06:19:00","flight":"DY359"},{"day":4,"utc":"16:07:00","flight":"DY198"},{"day":4,"utc":"02:28:00","flight":"DY670"},{"day":4,"utc":"15:18:00","flight":"DY673"},{"day":4,"utc":"11:26:00","flight":"DY392"},{"day":4,"utc":"12:56:00","flight":"DY814"},{"day":5,"utc":"08:22:00","flight":"DY576"},{"day":5,"utc":"15:57:00","flight":"DY645"},{"day":6,"utc":"19:57:00","flight":"DY846"}],"distance":1110.9546395983257}