{"id":36273,"type":"route","airline":"KL","airlineid":"airline_3090","sourceairport":"AMS","destinationairport":"NTE","stops":0,"equipment":"ERJ","schedule":[{"day":0,"utc":"10:08:00","flight":"KL004"},{"day":0,"utc":"16:04:00","flight":"KL266"},{"day":0,"utc":"17:41:00","flight":"KL255"},{"day":0,"utc":"12:35:00","flight":"KL297"},{"day":1,"utc":"09:08:00","flight":"KL772"},{"day":1,"utc":"01:10:00","flight":"KL903"},{"day":1,"utc":"09:46:00","flight":"KL889"},{"day":1,"utc":"03:29:00","flight":"KL003"},{"day":2,"utc":"11:43:00","flight":"KL082"},{"day":3,"utc":"15:13:00","flight":"KL975"},{"day":3,"utc":"00:11:00","flight":"KL157"},{"day":4,"utc":"00:07:00","flight":"KL854"},{"day":4,"utc":"06:59:00","flight":"KL215"},{"day":4,"utc":"20:42:00","flight":"KL994"},{"day":4,"utc":"16:02:00","flight":"KL453"},{"day":5,"utc":"01:53:00","flight":"KL152"},{"day":6,"utc":"12:37:00","flight":"KL873"},{"day":6,"utc":"14:39:00","flight":"KL809"},{"day":6,"utc":"05:10:00","flight":"KL451"},{"day":6,"utc":"01:13:00","flight":"KL166"}],"distance":733.2682625511252}