{"id":9975,"type":"route","airline":"AF","airlineid":"airline_137","sourceairport":"SXB","destinationairport":"AMS","stops":0,"equipment":"ER4 CR7 E70","schedule":[{"day":0,"utc":"19:20:00","flight":"AF216"},{"day":0,"utc":"21:05:00","flight":"AF755"},{"day":0,"utc":"14:08:00","flight":"AF993"},{"day":0,"utc":"15:24:00","flight":"AF575"},{"day":0,"utc":"05:57:00","flight":"AF368"},{"day":1,"utc":"03:46:00","flight":"AF941"},{"day":1,"utc":"10:00:00","flight":"AF123"},{"day":1,"utc":"17:26:00","flight":"AF791"},{"day":2,"utc":"08:24:00","flight":"AF005"},{"day":2,"utc":"01:24:00","flight":"AF933"},{"day":2,"utc":"18:07:00","flight":"AF299"},{"day":2,"utc":"11:02:00","flight":"AF663"},{"day":3,"utc":"00:46:00","flight":"AF904"},{"day":3,"utc":"21:10:00","flight":"AF736"},{"day":4,"utc":"12:52:00","flight":"AF676"},{"day":4,"utc":"06:06:00","flight":"AF774"},{"day":4,"utc":"00:23:00","flight":"AF251"},{"day":5,"utc":"03:07:00","flight":"AF461"},{"day":5,"utc":"08:22:00","flight":"AF919"},{"day":5,"utc":"00:22:00","flight":"AF420"},{"day":5,"utc":"07:24:00","flight":"AF578"},{"day":5,"utc":"10:05:00","flight":"AF442"},{"day":6,"utc":"13:13:00","flight":"AF517"},{"day":6,"utc":"21:38:00","flight":"AF685"},{"day":6,"utc":"15:04:00","flight":"AF381"},{"day":6,"utc":"03:22:00","flight":"AF351"}],"distance":465.6728273012158}