{"id":60705,"type":"route","airline":"UX","airlineid":"airline_90","sourceairport":"VGO","destinationairport":"CDG","stops":0,"equipment":"E90","schedule":[{"day":0,"utc":"01:32:00","flight":"UX727"},{"day":1,"utc":"11:19:00","flight":"UX635"},{"day":1,"utc":"06:51:00","flight":"UX518"},{"day":1,"utc":"22:58:00","flight":"UX889"},{"day":1,"utc":"19:21:00","flight":"UX577"},{"day":1,"utc":"08:21:00","flight":"UX967"},{"day":2,"utc":"15:37:00","flight":"UX571"},{"day":2,"utc":"21:28:00","flight":"UX577"},{"day":2,"utc":"02:15:00","flight":"UX393"},{"day":2,"utc":"19:33:00","flight":"UX893"},{"day":3,"utc":"13:49:00","flight":"UX524"},{"day":3,"utc":"21:49:00","flight":"UX482"},{"day":3,"utc":"06:01:00","flight":"UX451"},{"day":3,"utc":"16:04:00","flight":"UX521"},{"day":4,"utc":"03:49:00","flight":"UX425"},{"day":4,"utc":"03:24:00","flight":"UX781"},{"day":5,"utc":"13:54:00","flight":"UX457"},{"day":6,"utc":"11:56:00","flight":"UX539"},{"day":6,"utc":"19:47:00","flight":"UX412"},{"day":6,"utc":"22:23:00","flight":"UX738"},{"day":6,"utc":"10:45:00","flight":"UX267"}],"distance":1148.547843700282}