{"id":59899,"type":"route","airline":"US","airlineid":"airline_5265","sourceairport":"ORD","destinationairport":"DFW","stops":0,"equipment":"M80 M83 738","schedule":[{"day":0,"utc":"08:34:00","flight":"US265"},{"day":0,"utc":"13:52:00","flight":"US703"},{"day":0,"utc":"16:24:00","flight":"US486"},{"day":0,"utc":"08:34:00","flight":"US528"},{"day":1,"utc":"14:10:00","flight":"US583"},{"day":1,"utc":"14:58:00","flight":"US314"},{"day":2,"utc":"11:39:00","flight":"US325"},{"day":2,"utc":"22:50:00","flight":"US811"},{"day":2,"utc":"01:02:00","flight":"US160"},{"day":2,"utc":"07:02:00","flight":"US905"},{"day":3,"utc":"19:13:00","flight":"US700"},{"day":3,"utc":"09:55:00","flight":"US792"},{"day":3,"utc":"03:55:00","flight":"US300"},{"day":3,"utc":"11:32:00","flight":"US561"},{"day":3,"utc":"11:49:00","flight":"US793"},{"day":4,"utc":"01:24:00","flight":"US140"},{"day":4,"utc":"10:05:00","flight":"US092"},{"day":4,"utc":"17:00:00","flight":"US363"},{"day":4,"utc":"17:12:00","flight":"US613"},{"day":5,"utc":"20:59:00","flight":"US677"},{"day":6,"utc":"12:08:00","flight":"US516"},{"day":6,"utc":"05:18:00","flight":"US274"},{"day":6,"utc":"23:10:00","flight":"US634"}],"distance":1290.640549573098}