{"id":5421,"type":"route","airline":"AA","airlineid":"airline_24","sourceairport":"FCO","destinationairport":"JFK","stops":0,"equipment":"763","schedule":[{"day":0,"utc":"00:30:00","flight":"AA707"},{"day":0,"utc":"10:55:00","flight":"AA824"},{"day":0,"utc":"16:18:00","flight":"AA625"},{"day":0,"utc":"04:15:00","flight":"AA975"},{"day":1,"utc":"07:17:00","flight":"AA879"},{"day":1,"utc":"06:28:00","flight":"AA014"},{"day":2,"utc":"22:00:00","flight":"AA004"},{"day":2,"utc":"15:30:00","flight":"AA302"},{"day":2,"utc":"12:03:00","flight":"AA597"},{"day":3,"utc":"23:58:00","flight":"AA813"},{"day":3,"utc":"11:55:00","flight":"AA577"},{"day":4,"utc":"06:33:00","flight":"AA525"},{"day":5,"utc":"17:26:00","flight":"AA676"},{"day":5,"utc":"20:25:00","flight":"AA861"},{"day":5,"utc":"01:50:00","flight":"AA381"},{"day":5,"utc":"13:54:00","flight":"AA579"},{"day":5,"utc":"11:59:00","flight":"AA067"},{"day":6,"utc":"01:25:00","flight":"AA108"},{"day":6,"utc":"20:59:00","flight":"AA714"}],"distance":6866.316349632425}