{"id":16562,"type":"route","airline":"CA","airlineid":"airline_751","sourceairport":"LHR","destinationairport":"PVG","stops":0,"equipment":"346","schedule":[{"day":0,"utc":"10:11:00","flight":"CA397"},{"day":0,"utc":"18:42:00","flight":"CA218"},{"day":0,"utc":"16:10:00","flight":"CA106"},{"day":0,"utc":"08:41:00","flight":"CA230"},{"day":0,"utc":"02:46:00","flight":"CA646"},{"day":1,"utc":"04:27:00","flight":"CA174"},{"day":1,"utc":"19:08:00","flight":"CA835"},{"day":2,"utc":"06:34:00","flight":"CA087"},{"day":2,"utc":"02:25:00","flight":"CA418"},{"day":3,"utc":"01:04:00","flight":"CA100"},{"day":3,"utc":"15:03:00","flight":"CA798"},{"day":3,"utc":"20:22:00","flight":"CA119"},{"day":3,"utc":"13:06:00","flight":"CA109"},{"day":3,"utc":"01:54:00","flight":"CA115"},{"day":4,"utc":"12:22:00","flight":"CA287"},{"day":4,"utc":"01:09:00","flight":"CA256"},{"day":5,"utc":"19:40:00","flight":"CA763"},{"day":5,"utc":"16:03:00","flight":"CA536"},{"day":5,"utc":"00:58:00","flight":"CA577"},{"day":5,"utc":"08:33:00","flight":"CA981"},{"day":6,"utc":"18:15:00","flight":"CA260"},{"day":6,"utc":"04:22:00","flight":"CA428"},{"day":6,"utc":"12:51:00","flight":"CA488"}],"distance":9240.882996822049}