{"id":4535,"type":"route","airline":"A5","airlineid":"airline_1203","sourceairport":"LIL","destinationairport":"BOD","stops":0,"equipment":"E70 CR7 E90","schedule":[{"day":0,"utc":"02:02:00","flight":"A5224"},{"day":0,"utc":"23:58:00","flight":"A5536"},{"day":0,"utc":"00:35:00","flight":"A5090"},{"day":1,"utc":"02:07:00","flight":"A5605"},{"day":1,"utc":"11:04:00","flight":"A5947"},{"day":1,"utc":"18:09:00","flight":"A5444"},{"day":1,"utc":"11:58:00","flight":"A5524"},{"day":2,"utc":"22:46:00","flight":"A5920"},{"day":2,"utc":"23:14:00","flight":"A5383"},{"day":2,"utc":"22:00:00","flight":"A5214"},{"day":2,"utc":"05:31:00","flight":"A5201"},{"day":3,"utc":"10:40:00","flight":"A5248"},{"day":3,"utc":"03:16:00","flight":"A5986"},{"day":3,"utc":"05:49:00","flight":"A5368"},{"day":4,"utc":"17:41:00","flight":"A5812"},{"day":4,"utc":"22:01:00","flight":"A5664"},{"day":4,"utc":"14:33:00","flight":"A5910"},{"day":4,"utc":"00:32:00","flight":"A5103"},{"day":4,"utc":"00:43:00","flight":"A5726"},{"day":5,"utc":"00:16:00","flight":"A5517"},{"day":5,"utc":"22:43:00","flight":"A5778"},{"day":5,"utc":"00:27:00","flight":"A5963"},{"day":5,"utc":"10:03:00","flight":"A5541"},{"day":5,"utc":"13:35:00","flight":"A5217"},{"day":6,"utc":"03:59:00","flight":"A5025"},{"day":6,"utc":"13:09:00","flight":"A5384"},{"day":6,"utc":"12:21:00","flight":"A5150"},{"day":6,"utc":"14:42:00","flight":"A5885"}],"distance":698.0225539206731}