{"id":13973,"type":"route","airline":"B6","airlineid":"airline_3029","sourceairport":"CUN","destinationairport":"BOS","stops":0,"equipment":"320","schedule":[{"day":0,"utc":"01:16:00","flight":"B6510"},{"day":0,"utc":"03:44:00","flight":"B6781"},{"day":1,"utc":"17:54:00","flight":"B6956"},{"day":1,"utc":"16:14:00","flight":"B6735"},{"day":2,"utc":"10:19:00","flight":"B6520"},{"day":2,"utc":"18:21:00","flight":"B6508"},{"day":2,"utc":"18:13:00","flight":"B6708"},{"day":2,"utc":"13:39:00","flight":"B6435"},{"day":3,"utc":"10:16:00","flight":"B6310"},{"day":3,"utc":"23:20:00","flight":"B6300"},{"day":3,"utc":"07:05:00","flight":"B6299"},{"day":3,"utc":"07:25:00","flight":"B6560"},{"day":4,"utc":"00:52:00","flight":"B6369"},{"day":4,"utc":"00:49:00","flight":"B6419"},{"day":4,"utc":"05:41:00","flight":"B6433"},{"day":5,"utc":"17:22:00","flight":"B6244"},{"day":5,"utc":"15:10:00","flight":"B6804"},{"day":5,"utc":"01:47:00","flight":"B6683"},{"day":6,"utc":"09:31:00","flight":"B6753"},{"day":6,"utc":"06:28:00","flight":"B6029"},{"day":6,"utc":"05:32:00","flight":"B6932"},{"day":6,"utc":"13:40:00","flight":"B6931"},{"day":6,"utc":"18:10:00","flight":"B6153"}],"distance":2796.1820309260193}