{"title":"San Diego/Old Town-Mission Valley","name":"Handlery Hotel","address":"950 Hotel Circle North","directions":null,"phone":"+1 619 298-0511","tollfree":null,"email":null,"fax":null,"url":"http://sd.handlery.com/","checkin":null,"checkout":null,"price":null,"geo":{"lat":32.76105,"lon":-117.1732,"accuracy":"ROOFTOP"},"type":"hotel","id":25302,"country":"United States","city":"San Diego","state":"California","reviews":[{"content":"This is a great hotel. The staff was friendly, the rooms were clean and nice and its in a great location. The hotels located nearby, in Hotel Circle, seem run down and this is a nice alternative while still be near the shopping and restuarants. I'll definitely stay here again.","ratings":{"Service":5.0,"Cleanliness":5.0,"Overall":5.0,"Value":5.0,"Location":5.0,"Rooms":5.0},"author":"Francis Powlowski","date":"2014-09-11 05:21:13 +0300"}],"public_likes":["Sonny Will","Sigurd O'Reilly PhD","Andres Schultz","Rhett Kreiger","Mrs. Leta Ondricka","Marcellus Schaden","Philip Anderson"],"vacancy":false,"description":"A warm, friendly welcome and some big, lush rooms.  Also has a hotel mini-bus to take you to SeaWorld.","alias":null,"pets_ok":true,"free_breakfast":true,"free_internet":true,"free_parking":false}