{"title":"London/Holborn-Clerkenwell","name":"The Honorable Society of Lincoln's Inn","alt":"Lincoln's Inn","address":"Lincoln's Inn Fields, WC2A 3TL","directions":"tube: Holborn ''or'' Chancery Lane","phone":"+44 20 7405-1393","tollfree":null,"email":"mail@lincolnsinn.org.uk","url":"http://www.lincolnsinn.org.uk/","hours":null,"image":"https://en.wikivoyage.org/wiki/File:Gateway to Lincoln's Inn, off Lincoln's Inn.jpeg","price":null,"content":"Like Gray's Inn, one the of the four societies of the bar. The wonderful old buildings here are arranged around the open spaces of Lincoln's Inn Fields and a walk around this area will give any visitor a real sense of the history and grand traditions of the legal profession in London. | image=Gateway to Lincoln's Inn, off Lincoln's Inn.jpeg","geo":{"lat":51.5171,"lon":-0.1146,"accuracy":"RANGE_INTERPOLATED"},"activity":"see","type":"landmark","id":16186,"country":"United Kingdom","city":"London","state":null,"image_direct_url":"https://upload.wikimedia.org/wikipedia/commons/e/e6/Gateway_to_Lincoln%27s_Inn%2C_off_Lincoln%27s_Inn.jpeg"}