{"title":"Annan","name":"Cafe Royal","alt":null,"address":"95 High St, DG12 6DJ","directions":null,"phone":"+44 1461 202865","tollfree":null,"email":null,"url":null,"hours":"08:00 - 20:00","image":null,"price":null,"content":"Fish & Chips, sit in and takeaway. It is family run. Closes relatively early, don't expect it to be open when you leave the pub.","geo":{"lat":54.98732,"lon":-3.25955,"accuracy":"RANGE_INTERPOLATED"},"activity":"eat","type":"landmark","id":37329,"country":"United Kingdom","city":"Annan","state":null}