{"title":"Wales Coast Path","name":"Carreg Coetan Arthur Burial Chamber","alt":null,"address":null,"directions":null,"phone":null,"tollfree":null,"email":null,"url":"http://cadw.wales.gov.uk/daysout/carregcoetanburialchamber/?lang=en","hours":null,"image":"https://en.wikivoyage.org/wiki/File:Carreg Coetan burial chamber. - geograph.org.uk - 1044642.jpg","price":null,"content":"Neolithic burial chamber","geo":{"lat":52.018229,"lon":-4.827242,"accuracy":"RANGE_INTERPOLATED"},"activity":"see","type":"landmark","id":40063,"country":"United Kingdom","city":"Newport","state":null,"image_direct_url":"https://upload.wikimedia.org/wikipedia/commons/c/cb/Carreg_Coetan_burial_chamber._-_geograph.org.uk_-_1044642.jpg"}