{"title":"Liverpool","name":"Everton FC","alt":null,"address":"Goodison Rd, Liverpool, Merseyside L4 4EL","directions":null,"phone":"+44 871 663 1878","tollfree":null,"email":null,"url":"http://www.evertonfc.com/","hours":null,"image":null,"price":null,"content":"The self-styled 'Peoples Club' of Liverpool, Everton is one of the oldest football clubs in England and are one of the most successful clubs in England. Fans of Everton are known as &quot;Toffees&quot;. They play at Goodison Park, one of the oldest football grounds in England, it is known for its excellent atmosphere. The stadium can be reached via soccerbuses from Sandhills Station or a taxi, normally costing £6 from Lime Street station. Tickets are available from the Fan Centre behind the Park End of the stadium or online at www.evertonfc.com. Club Merchandise is available from the Everton One Megastore opposite the Park End of the ground, or Everton Two in the Liverpool One Complex. The Winslow Hotel on Goodison Road, opposite the Main Stand at Goodison, is the closest public house. Food is available on the concourses, along with beer in the form of club sponsors Chang. For those on a restricted wallet plus with a sweeter tooth, there is a tea and cake sale held before every match in the hall of St Luke's Church, located on the corner of Goodison Road and Gwladys Street.","geo":{"lat":53.438977,"lon":-2.967498,"accuracy":"APPROXIMATE"},"activity":"do","type":"landmark","id":15865,"country":"United Kingdom","city":"Liverpool","state":null}