{"title":"Paris/7th arrondissement","name":"Rue Cler","alt":null,"address":"rue cler","directions":"Ecole Militaire","phone":null,"tollfree":null,"email":null,"url":null,"hours":null,"image":null,"price":null,"content":"Market street 10 minutes from the Eiffel Tower. The market is at its best on Tu–Sa, 08:30–13:00 or 15:00–19:30; Su, 08:30–12:00; closed on M.","geo":{"lat":48.85657,"lon":2.30652,"accuracy":"APPROXIMATE"},"activity":"buy","type":"landmark","id":21808,"country":"France","city":"Paris","state":"Île-de-France"}