{"title":"Los Angeles/Northwest","name":"4100 Bar","alt":null,"address":"4100 W Sunset Blvd","directions":null,"phone":"+1 323 666-4460","tollfree":null,"email":null,"url":"http://213nightlife.com/4100bar","hours":"6PM-2AM daily","image":null,"price":null,"content":"Once a leather daddy bar, this has turned into one of the newer hip bars in the area.","geo":{"lat":34.093039,"lon":-118.281454,"accuracy":"ROOFTOP"},"activity":"drink","type":"landmark","id":35065,"country":"United States","city":"Los Angeles","state":"California"}