{"id":14596,"type":"route","airline":"BA","airlineid":"airline_1355","sourceairport":"LCY","destinationairport":"ABZ","stops":0,"equipment":"E70 S20","schedule":[{"day":0,"utc":"04:53:00","flight":"BA768"},{"day":0,"utc":"05:45:00","flight":"BA402"},{"day":0,"utc":"11:26:00","flight":"BA761"},{"day":1,"utc":"08:05:00","flight":"BA813"},{"day":1,"utc":"03:19:00","flight":"BA905"},{"day":1,"utc":"11:50:00","flight":"BA458"},{"day":2,"utc":"13:48:00","flight":"BA811"},{"day":2,"utc":"16:37:00","flight":"BA400"},{"day":2,"utc":"23:00:00","flight":"BA812"},{"day":3,"utc":"10:43:00","flight":"BA784"},{"day":3,"utc":"01:36:00","flight":"BA723"},{"day":3,"utc":"01:45:00","flight":"BA837"},{"day":3,"utc":"09:21:00","flight":"BA160"},{"day":3,"utc":"16:17:00","flight":"BA454"},{"day":4,"utc":"22:40:00","flight":"BA161"},{"day":4,"utc":"05:52:00","flight":"BA442"},{"day":4,"utc":"21:41:00","flight":"BA776"},{"day":5,"utc":"09:37:00","flight":"BA086"},{"day":5,"utc":"10:18:00","flight":"BA985"},{"day":5,"utc":"22:32:00","flight":"BA375"},{"day":6,"utc":"12:14:00","flight":"BA795"},{"day":6,"utc":"01:45:00","flight":"BA402"},{"day":6,"utc":"20:30:00","flight":"BA760"},{"day":6,"utc":"10:57:00","flight":"BA518"}],"distance":649.9551811425955}