{"id":25303,"type":"route","airline":"FL","airlineid":"airline_1316","sourceairport":"MEM","destinationairport":"HOU","stops":0,"equipment":"733","schedule":[{"day":0,"utc":"11:07:00","flight":"FL499"},{"day":0,"utc":"16:23:00","flight":"FL331"},{"day":0,"utc":"11:50:00","flight":"FL553"},{"day":0,"utc":"08:14:00","flight":"FL782"},{"day":1,"utc":"18:51:00","flight":"FL974"},{"day":1,"utc":"03:37:00","flight":"FL744"},{"day":1,"utc":"00:17:00","flight":"FL285"},{"day":1,"utc":"05:08:00","flight":"FL658"},{"day":1,"utc":"09:25:00","flight":"FL726"},{"day":2,"utc":"22:41:00","flight":"FL342"},{"day":2,"utc":"09:52:00","flight":"FL387"},{"day":2,"utc":"09:10:00","flight":"FL833"},{"day":2,"utc":"05:12:00","flight":"FL263"},{"day":2,"utc":"13:20:00","flight":"FL991"},{"day":3,"utc":"06:50:00","flight":"FL011"},{"day":3,"utc":"18:23:00","flight":"FL017"},{"day":3,"utc":"05:26:00","flight":"FL462"},{"day":4,"utc":"09:54:00","flight":"FL161"},{"day":4,"utc":"02:28:00","flight":"FL050"},{"day":4,"utc":"23:06:00","flight":"FL231"},{"day":5,"utc":"08:40:00","flight":"FL950"},{"day":6,"utc":"19:42:00","flight":"FL275"},{"day":6,"utc":"21:08:00","flight":"FL988"},{"day":6,"utc":"02:39:00","flight":"FL368"},{"day":6,"utc":"09:35:00","flight":"FL881"}],"distance":779.6146821150392}