{"id":14778,"type":"route","airline":"BA","airlineid":"airline_1355","sourceairport":"LHR","destinationairport":"TLS","stops":0,"equipment":"319 320 321","schedule":[{"day":0,"utc":"14:19:00","flight":"BA995"},{"day":0,"utc":"23:19:00","flight":"BA193"},{"day":0,"utc":"20:14:00","flight":"BA265"},{"day":0,"utc":"16:50:00","flight":"BA584"},{"day":0,"utc":"21:58:00","flight":"BA183"},{"day":1,"utc":"14:30:00","flight":"BA343"},{"day":1,"utc":"04:16:00","flight":"BA762"},{"day":2,"utc":"10:15:00","flight":"BA479"},{"day":3,"utc":"17:15:00","flight":"BA708"},{"day":3,"utc":"04:09:00","flight":"BA450"},{"day":4,"utc":"10:52:00","flight":"BA645"},{"day":4,"utc":"22:18:00","flight":"BA103"},{"day":5,"utc":"12:27:00","flight":"BA163"},{"day":6,"utc":"08:53:00","flight":"BA590"},{"day":6,"utc":"09:51:00","flight":"BA132"},{"day":6,"utc":"23:59:00","flight":"BA565"}],"distance":883.3122325423356}