{"id":13455,"type":"route","airline":"AZ","airlineid":"airline_596","sourceairport":"LHR","destinationairport":"LIN","stops":0,"equipment":"32S 320 321","schedule":[{"day":0,"utc":"12:02:00","flight":"AZ824"},{"day":0,"utc":"00:43:00","flight":"AZ857"},{"day":0,"utc":"04:54:00","flight":"AZ166"},{"day":0,"utc":"22:29:00","flight":"AZ122"},{"day":1,"utc":"19:57:00","flight":"AZ736"},{"day":1,"utc":"22:37:00","flight":"AZ796"},{"day":2,"utc":"13:11:00","flight":"AZ005"},{"day":2,"utc":"11:37:00","flight":"AZ519"},{"day":2,"utc":"21:47:00","flight":"AZ751"},{"day":3,"utc":"17:40:00","flight":"AZ090"},{"day":3,"utc":"07:09:00","flight":"AZ852"},{"day":3,"utc":"00:21:00","flight":"AZ210"},{"day":3,"utc":"22:03:00","flight":"AZ397"},{"day":4,"utc":"01:26:00","flight":"AZ900"},{"day":4,"utc":"23:51:00","flight":"AZ144"},{"day":4,"utc":"11:18:00","flight":"AZ483"},{"day":4,"utc":"13:13:00","flight":"AZ943"},{"day":4,"utc":"12:03:00","flight":"AZ478"},{"day":5,"utc":"15:22:00","flight":"AZ957"},{"day":5,"utc":"12:21:00","flight":"AZ220"},{"day":5,"utc":"16:29:00","flight":"AZ034"},{"day":5,"utc":"02:51:00","flight":"AZ882"},{"day":6,"utc":"05:58:00","flight":"AZ732"},{"day":6,"utc":"00:47:00","flight":"AZ063"}],"distance":981.0919317280961}