{"id":60364,"type":"route","airline":"US","airlineid":"airline_5265","sourceairport":"SGF","destinationairport":"DFW","stops":0,"equipment":"ER4 ERD","schedule":[{"day":0,"utc":"19:01:00","flight":"US901"},{"day":0,"utc":"07:15:00","flight":"US250"},{"day":0,"utc":"07:46:00","flight":"US928"},{"day":0,"utc":"11:24:00","flight":"US465"},{"day":0,"utc":"15:37:00","flight":"US354"},{"day":1,"utc":"08:55:00","flight":"US909"},{"day":1,"utc":"23:16:00","flight":"US965"},{"day":1,"utc":"23:55:00","flight":"US755"},{"day":1,"utc":"01:39:00","flight":"US918"},{"day":2,"utc":"03:57:00","flight":"US845"},{"day":2,"utc":"17:40:00","flight":"US395"},{"day":2,"utc":"22:04:00","flight":"US110"},{"day":2,"utc":"09:31:00","flight":"US443"},{"day":3,"utc":"11:26:00","flight":"US688"},{"day":3,"utc":"04:32:00","flight":"US508"},{"day":3,"utc":"05:05:00","flight":"US706"},{"day":3,"utc":"14:25:00","flight":"US971"},{"day":4,"utc":"10:21:00","flight":"US968"},{"day":4,"utc":"06:02:00","flight":"US604"},{"day":4,"utc":"21:25:00","flight":"US033"},{"day":5,"utc":"10:44:00","flight":"US406"},{"day":5,"utc":"06:35:00","flight":"US597"},{"day":6,"utc":"04:55:00","flight":"US118"},{"day":6,"utc":"23:30:00","flight":"US781"},{"day":6,"utc":"07:14:00","flight":"US119"},{"day":6,"utc":"08:20:00","flight":"US004"},{"day":6,"utc":"21:55:00","flight":"US259"}],"distance":586.5108494260279}