{"id":35049,"type":"route","airline":"JQ","airlineid":"airline_3052","sourceairport":"SYD","destinationairport":"HNL","stops":0,"equipment":"332","schedule":[{"day":0,"utc":"20:15:00","flight":"JQ256"},{"day":0,"utc":"22:16:00","flight":"JQ916"},{"day":0,"utc":"15:25:00","flight":"JQ449"},{"day":1,"utc":"13:26:00","flight":"JQ445"},{"day":1,"utc":"12:03:00","flight":"JQ451"},{"day":2,"utc":"22:48:00","flight":"JQ007"},{"day":3,"utc":"14:09:00","flight":"JQ048"},{"day":3,"utc":"18:32:00","flight":"JQ553"},{"day":3,"utc":"21:50:00","flight":"JQ655"},{"day":3,"utc":"06:45:00","flight":"JQ672"},{"day":4,"utc":"14:46:00","flight":"JQ493"},{"day":4,"utc":"00:04:00","flight":"JQ744"},{"day":4,"utc":"04:00:00","flight":"JQ754"},{"day":4,"utc":"18:03:00","flight":"JQ549"},{"day":4,"utc":"06:36:00","flight":"JQ132"},{"day":5,"utc":"00:37:00","flight":"JQ755"},{"day":6,"utc":"20:38:00","flight":"JQ153"},{"day":6,"utc":"11:55:00","flight":"JQ855"}],"distance":8170.485015880451}