{"id":9247,"type":"route","airline":"AF","airlineid":"airline_137","sourceairport":"CAE","destinationairport":"ATL","stops":0,"equipment":"CRJ M88 319 717","schedule":[{"day":0,"utc":"22:47:00","flight":"AF568"},{"day":1,"utc":"13:40:00","flight":"AF776"},{"day":1,"utc":"14:53:00","flight":"AF309"},{"day":1,"utc":"12:13:00","flight":"AF374"},{"day":1,"utc":"08:11:00","flight":"AF711"},{"day":2,"utc":"03:57:00","flight":"AF952"},{"day":3,"utc":"00:58:00","flight":"AF687"},{"day":3,"utc":"06:24:00","flight":"AF541"},{"day":3,"utc":"20:59:00","flight":"AF278"},{"day":3,"utc":"13:38:00","flight":"AF457"},{"day":4,"utc":"07:33:00","flight":"AF781"},{"day":4,"utc":"05:15:00","flight":"AF983"},{"day":5,"utc":"19:00:00","flight":"AF943"},{"day":5,"utc":"15:17:00","flight":"AF230"},{"day":5,"utc":"15:52:00","flight":"AF813"},{"day":5,"utc":"07:51:00","flight":"AF171"},{"day":6,"utc":"08:12:00","flight":"AF845"},{"day":6,"utc":"03:25:00","flight":"AF806"},{"day":6,"utc":"02:38:00","flight":"AF128"}],"distance":307.5828596334743}