{"id":47226,"type":"route","airline":"QH","airlineid":"airline_882","sourceairport":"CEK","destinationairport":"FRU","stops":0,"equipment":"735","schedule":[{"day":0,"utc":"19:33:00","flight":"QH469"},{"day":1,"utc":"19:06:00","flight":"QH675"},{"day":2,"utc":"08:07:00","flight":"QH979"},{"day":2,"utc":"09:20:00","flight":"QH064"},{"day":3,"utc":"13:43:00","flight":"QH691"},{"day":3,"utc":"11:45:00","flight":"QH169"},{"day":4,"utc":"23:35:00","flight":"QH720"},{"day":4,"utc":"18:08:00","flight":"QH952"},{"day":4,"utc":"07:14:00","flight":"QH393"},{"day":4,"utc":"06:48:00","flight":"QH482"},{"day":4,"utc":"15:43:00","flight":"QH062"},{"day":5,"utc":"11:03:00","flight":"QH481"},{"day":5,"utc":"00:44:00","flight":"QH615"},{"day":5,"utc":"20:21:00","flight":"QH514"},{"day":5,"utc":"11:11:00","flight":"QH304"},{"day":6,"utc":"14:52:00","flight":"QH819"}],"distance":1650.3834092569045}