{"id":9801,"type":"route","airline":"AF","airlineid":"airline_137","sourceairport":"NCE","destinationairport":"LYS","stops":0,"equipment":"320 319","schedule":[{"day":0,"utc":"20:57:00","flight":"AF696"},{"day":0,"utc":"21:15:00","flight":"AF139"},{"day":0,"utc":"06:44:00","flight":"AF997"},{"day":0,"utc":"09:48:00","flight":"AF646"},{"day":0,"utc":"14:00:00","flight":"AF038"},{"day":1,"utc":"15:05:00","flight":"AF813"},{"day":2,"utc":"01:45:00","flight":"AF807"},{"day":2,"utc":"15:29:00","flight":"AF828"},{"day":2,"utc":"08:41:00","flight":"AF262"},{"day":3,"utc":"06:47:00","flight":"AF026"},{"day":3,"utc":"18:32:00","flight":"AF047"},{"day":3,"utc":"17:06:00","flight":"AF338"},{"day":3,"utc":"09:23:00","flight":"AF069"},{"day":3,"utc":"01:43:00","flight":"AF532"},{"day":4,"utc":"17:23:00","flight":"AF897"},{"day":4,"utc":"05:14:00","flight":"AF127"},{"day":4,"utc":"07:37:00","flight":"AF126"},{"day":4,"utc":"04:02:00","flight":"AF519"},{"day":5,"utc":"11:11:00","flight":"AF785"},{"day":5,"utc":"03:56:00","flight":"AF800"},{"day":5,"utc":"16:21:00","flight":"AF143"},{"day":5,"utc":"21:20:00","flight":"AF862"},{"day":5,"utc":"02:19:00","flight":"AF226"},{"day":6,"utc":"03:15:00","flight":"AF398"}],"distance":284.7449727949726}