{"id":29140,"type":"route","airline":"G4","airlineid":"airline_35","sourceairport":"PVU","destinationairport":"AZA","stops":0,"equipment":"319","schedule":[{"day":0,"utc":"13:17:00","flight":"G4367"},{"day":0,"utc":"16:18:00","flight":"G4616"},{"day":0,"utc":"05:06:00","flight":"G4901"},{"day":0,"utc":"05:55:00","flight":"G4746"},{"day":1,"utc":"19:38:00","flight":"G4279"},{"day":1,"utc":"13:36:00","flight":"G4280"},{"day":2,"utc":"04:37:00","flight":"G4382"},{"day":2,"utc":"10:34:00","flight":"G4716"},{"day":2,"utc":"20:23:00","flight":"G4800"},{"day":3,"utc":"16:24:00","flight":"G4058"},{"day":3,"utc":"17:31:00","flight":"G4557"},{"day":3,"utc":"16:47:00","flight":"G4325"},{"day":4,"utc":"12:36:00","flight":"G4178"},{"day":4,"utc":"20:06:00","flight":"G4278"},{"day":4,"utc":"18:49:00","flight":"G4888"},{"day":4,"utc":"14:19:00","flight":"G4625"},{"day":4,"utc":"23:40:00","flight":"G4114"},{"day":5,"utc":"02:08:00","flight":"G4307"},{"day":5,"utc":"20:49:00","flight":"G4398"},{"day":5,"utc":"01:43:00","flight":"G4574"},{"day":5,"utc":"05:25:00","flight":"G4847"},{"day":6,"utc":"06:25:00","flight":"G4541"},{"day":6,"utc":"03:19:00","flight":"G4887"},{"day":6,"utc":"02:20:00","flight":"G4026"},{"day":6,"utc":"07:16:00","flight":"G4701"},{"day":6,"utc":"05:47:00","flight":"G4364"}],"distance":768.4049471137845}