{"id":9353,"type":"route","airline":"AF","airlineid":"airline_137","sourceairport":"CDG","destinationairport":"LUX","stops":0,"equipment":"ER4 DH4","schedule":[{"day":0,"utc":"14:18:00","flight":"AF861"},{"day":0,"utc":"21:11:00","flight":"AF468"},{"day":1,"utc":"06:21:00","flight":"AF340"},{"day":1,"utc":"13:32:00","flight":"AF297"},{"day":1,"utc":"03:23:00","flight":"AF795"},{"day":2,"utc":"17:43:00","flight":"AF761"},{"day":2,"utc":"16:58:00","flight":"AF006"},{"day":2,"utc":"13:39:00","flight":"AF323"},{"day":2,"utc":"04:37:00","flight":"AF983"},{"day":2,"utc":"19:12:00","flight":"AF928"},{"day":3,"utc":"21:27:00","flight":"AF268"},{"day":3,"utc":"01:56:00","flight":"AF107"},{"day":3,"utc":"23:19:00","flight":"AF802"},{"day":3,"utc":"08:46:00","flight":"AF184"},{"day":3,"utc":"12:20:00","flight":"AF889"},{"day":4,"utc":"07:26:00","flight":"AF788"},{"day":5,"utc":"16:56:00","flight":"AF821"},{"day":5,"utc":"10:32:00","flight":"AF485"},{"day":6,"utc":"17:16:00","flight":"AF701"},{"day":6,"utc":"06:40:00","flight":"AF607"},{"day":6,"utc":"04:35:00","flight":"AF280"},{"day":6,"utc":"20:20:00","flight":"AF025"},{"day":6,"utc":"12:45:00","flight":"AF808"}],"distance":273.99494257963664}