{"id":30272,"type":"route","airline":"GS","airlineid":"airline_690","sourceairport":"HLD","destinationairport":"HRB","stops":0,"equipment":"E90","schedule":[{"day":0,"utc":"07:34:00","flight":"GS994"},{"day":0,"utc":"00:15:00","flight":"GS523"},{"day":1,"utc":"22:19:00","flight":"GS235"},{"day":1,"utc":"07:21:00","flight":"GS022"},{"day":1,"utc":"06:44:00","flight":"GS203"},{"day":1,"utc":"02:05:00","flight":"GS417"},{"day":2,"utc":"18:28:00","flight":"GS919"},{"day":2,"utc":"07:38:00","flight":"GS812"},{"day":2,"utc":"16:02:00","flight":"GS841"},{"day":2,"utc":"03:52:00","flight":"GS530"},{"day":2,"utc":"00:15:00","flight":"GS815"},{"day":3,"utc":"02:52:00","flight":"GS482"},{"day":3,"utc":"03:58:00","flight":"GS937"},{"day":3,"utc":"11:30:00","flight":"GS556"},{"day":3,"utc":"18:40:00","flight":"GS335"},{"day":3,"utc":"10:16:00","flight":"GS414"},{"day":4,"utc":"01:58:00","flight":"GS026"},{"day":4,"utc":"07:16:00","flight":"GS178"},{"day":4,"utc":"18:32:00","flight":"GS134"},{"day":4,"utc":"10:39:00","flight":"GS716"},{"day":4,"utc":"14:21:00","flight":"GS714"},{"day":5,"utc":"02:02:00","flight":"GS959"},{"day":5,"utc":"16:08:00","flight":"GS513"},{"day":5,"utc":"10:58:00","flight":"GS310"},{"day":5,"utc":"06:16:00","flight":"GS210"},{"day":6,"utc":"07:12:00","flight":"GS629"},{"day":6,"utc":"10:14:00","flight":"GS350"},{"day":6,"utc":"00:37:00","flight":"GS718"},{"day":6,"utc":"17:44:00","flight":"GS342"},{"day":6,"utc":"19:29:00","flight":"GS740"}],"distance":625.9984153485939}