{"id":9796,"type":"route","airline":"AF","airlineid":"airline_137","sourceairport":"NCE","destinationairport":"CLY","stops":0,"equipment":"AT7","schedule":[{"day":0,"utc":"15:32:00","flight":"AF840"},{"day":1,"utc":"22:49:00","flight":"AF196"},{"day":1,"utc":"18:06:00","flight":"AF888"},{"day":1,"utc":"10:31:00","flight":"AF786"},{"day":2,"utc":"03:28:00","flight":"AF156"},{"day":2,"utc":"11:32:00","flight":"AF898"},{"day":3,"utc":"16:33:00","flight":"AF933"},{"day":3,"utc":"04:25:00","flight":"AF722"},{"day":3,"utc":"16:33:00","flight":"AF841"},{"day":3,"utc":"10:11:00","flight":"AF123"},{"day":3,"utc":"16:52:00","flight":"AF231"},{"day":4,"utc":"11:29:00","flight":"AF816"},{"day":4,"utc":"16:05:00","flight":"AF964"},{"day":4,"utc":"08:25:00","flight":"AF739"},{"day":4,"utc":"04:26:00","flight":"AF814"},{"day":5,"utc":"13:47:00","flight":"AF519"},{"day":5,"utc":"14:19:00","flight":"AF690"},{"day":5,"utc":"13:14:00","flight":"AF965"},{"day":5,"utc":"03:57:00","flight":"AF188"},{"day":5,"utc":"22:09:00","flight":"AF875"},{"day":6,"utc":"17:56:00","flight":"AF898"}],"distance":179.2295193754417}