{"id":9725,"type":"route","airline":"AF","airlineid":"airline_137","sourceairport":"MLB","destinationairport":"ATL","stops":0,"equipment":"M88","schedule":[{"day":0,"utc":"15:25:00","flight":"AF959"},{"day":1,"utc":"19:00:00","flight":"AF427"},{"day":1,"utc":"21:55:00","flight":"AF773"},{"day":2,"utc":"15:00:00","flight":"AF058"},{"day":2,"utc":"20:42:00","flight":"AF031"},{"day":3,"utc":"15:27:00","flight":"AF439"},{"day":3,"utc":"05:30:00","flight":"AF530"},{"day":4,"utc":"18:09:00","flight":"AF771"},{"day":4,"utc":"15:07:00","flight":"AF681"},{"day":5,"utc":"11:10:00","flight":"AF887"},{"day":5,"utc":"20:17:00","flight":"AF122"},{"day":5,"utc":"07:07:00","flight":"AF734"},{"day":6,"utc":"01:36:00","flight":"AF457"}],"distance":713.2899161596914}