{"id":57568,"type":"route","airline":"UA","airlineid":"airline_5209","sourceairport":"SAF","destinationairport":"DEN","stops":0,"equipment":"ERJ","schedule":[{"day":0,"utc":"23:50:00","flight":"UA138"},{"day":1,"utc":"10:53:00","flight":"UA656"},{"day":2,"utc":"17:38:00","flight":"UA328"},{"day":2,"utc":"08:26:00","flight":"UA964"},{"day":2,"utc":"17:22:00","flight":"UA967"},{"day":2,"utc":"05:41:00","flight":"UA497"},{"day":2,"utc":"20:42:00","flight":"UA992"},{"day":3,"utc":"06:27:00","flight":"UA691"},{"day":3,"utc":"13:12:00","flight":"UA400"},{"day":3,"utc":"11:03:00","flight":"UA020"},{"day":3,"utc":"07:57:00","flight":"UA796"},{"day":4,"utc":"07:34:00","flight":"UA178"},{"day":4,"utc":"00:35:00","flight":"UA774"},{"day":4,"utc":"22:55:00","flight":"UA632"},{"day":5,"utc":"02:35:00","flight":"UA228"},{"day":5,"utc":"09:07:00","flight":"UA009"},{"day":5,"utc":"09:35:00","flight":"UA761"},{"day":5,"utc":"02:36:00","flight":"UA582"},{"day":5,"utc":"06:30:00","flight":"UA441"},{"day":6,"utc":"17:17:00","flight":"UA119"},{"day":6,"utc":"06:46:00","flight":"UA411"},{"day":6,"utc":"22:41:00","flight":"UA273"},{"day":6,"utc":"05:08:00","flight":"UA137"}],"distance":488.1050923298954}