{"id":10206,"type":"route","airline":"AH","airlineid":"airline_794","sourceairport":"MRS","destinationairport":"CZL","stops":0,"equipment":"738","schedule":[{"day":0,"utc":"19:52:00","flight":"AH564"},{"day":1,"utc":"10:57:00","flight":"AH159"},{"day":1,"utc":"00:52:00","flight":"AH129"},{"day":1,"utc":"17:33:00","flight":"AH325"},{"day":1,"utc":"07:57:00","flight":"AH449"},{"day":2,"utc":"07:52:00","flight":"AH482"},{"day":3,"utc":"05:34:00","flight":"AH096"},{"day":3,"utc":"19:28:00","flight":"AH320"},{"day":4,"utc":"12:37:00","flight":"AH683"},{"day":4,"utc":"00:06:00","flight":"AH136"},{"day":5,"utc":"16:56:00","flight":"AH887"},{"day":6,"utc":"19:50:00","flight":"AH395"},{"day":6,"utc":"13:22:00","flight":"AH876"}],"distance":805.0723508105696}