{"id":9643,"type":"route","airline":"AF","airlineid":"airline_137","sourceairport":"LFT","destinationairport":"ATL","stops":0,"equipment":"CRJ","schedule":[{"day":0,"utc":"03:55:00","flight":"AF242"},{"day":1,"utc":"18:35:00","flight":"AF264"},{"day":2,"utc":"02:35:00","flight":"AF154"},{"day":2,"utc":"03:29:00","flight":"AF126"},{"day":2,"utc":"22:34:00","flight":"AF892"},{"day":2,"utc":"01:30:00","flight":"AF468"},{"day":2,"utc":"23:09:00","flight":"AF517"},{"day":3,"utc":"12:36:00","flight":"AF607"},{"day":4,"utc":"06:30:00","flight":"AF171"},{"day":4,"utc":"11:22:00","flight":"AF717"},{"day":5,"utc":"22:08:00","flight":"AF831"},{"day":5,"utc":"01:59:00","flight":"AF253"},{"day":5,"utc":"18:43:00","flight":"AF606"},{"day":6,"utc":"22:27:00","flight":"AF232"}],"distance":808.757078271883}