{"id":55952,"type":"route","airline":"UA","airlineid":"airline_5209","sourceairport":"CHS","destinationairport":"CLE","stops":0,"equipment":"ERJ","schedule":[{"day":0,"utc":"13:35:00","flight":"UA539"},{"day":0,"utc":"00:17:00","flight":"UA111"},{"day":0,"utc":"03:09:00","flight":"UA096"},{"day":0,"utc":"03:01:00","flight":"UA273"},{"day":1,"utc":"20:17:00","flight":"UA576"},{"day":1,"utc":"06:31:00","flight":"UA614"},{"day":2,"utc":"07:17:00","flight":"UA290"},{"day":2,"utc":"09:25:00","flight":"UA250"},{"day":3,"utc":"04:32:00","flight":"UA761"},{"day":3,"utc":"06:12:00","flight":"UA467"},{"day":3,"utc":"18:02:00","flight":"UA710"},{"day":3,"utc":"22:26:00","flight":"UA921"},{"day":4,"utc":"23:52:00","flight":"UA427"},{"day":4,"utc":"08:37:00","flight":"UA554"},{"day":5,"utc":"12:23:00","flight":"UA921"},{"day":5,"utc":"09:47:00","flight":"UA357"},{"day":5,"utc":"17:10:00","flight":"UA118"},{"day":6,"utc":"14:12:00","flight":"UA240"}],"distance":960.0233238382915}