{"id":2718,"type":"route","airline":"7H","airlineid":"airline_16726","sourceairport":"PIZ","destinationairport":"PHO","stops":0,"equipment":"BE1","schedule":[{"day":0,"utc":"10:22:00","flight":"7H182"},{"day":0,"utc":"05:58:00","flight":"7H617"},{"day":1,"utc":"12:05:00","flight":"7H304"},{"day":1,"utc":"06:14:00","flight":"7H636"},{"day":1,"utc":"01:01:00","flight":"7H767"},{"day":1,"utc":"21:32:00","flight":"7H153"},{"day":2,"utc":"21:24:00","flight":"7H159"},{"day":2,"utc":"21:47:00","flight":"7H260"},{"day":2,"utc":"00:17:00","flight":"7H197"},{"day":2,"utc":"03:17:00","flight":"7H996"},{"day":2,"utc":"04:42:00","flight":"7H705"},{"day":3,"utc":"03:37:00","flight":"7H747"},{"day":3,"utc":"16:42:00","flight":"7H706"},{"day":3,"utc":"16:02:00","flight":"7H403"},{"day":4,"utc":"15:38:00","flight":"7H238"},{"day":4,"utc":"02:16:00","flight":"7H054"},{"day":5,"utc":"00:07:00","flight":"7H813"},{"day":5,"utc":"02:04:00","flight":"7H412"},{"day":5,"utc":"22:10:00","flight":"7H268"},{"day":5,"utc":"00:47:00","flight":"7H281"},{"day":5,"utc":"18:12:00","flight":"7H501"},{"day":6,"utc":"00:08:00","flight":"7H541"},{"day":6,"utc":"23:39:00","flight":"7H426"}],"distance":215.46030675419257}