{"id":63437,"type":"route","airline":"WN","airlineid":"airline_4547","sourceairport":"AMA","destinationairport":"DEN","stops":0,"equipment":"735 73W","schedule":[{"day":0,"utc":"22:47:00","flight":"WN051"},{"day":0,"utc":"04:43:00","flight":"WN159"},{"day":0,"utc":"01:23:00","flight":"WN166"},{"day":1,"utc":"00:23:00","flight":"WN811"},{"day":2,"utc":"21:51:00","flight":"WN740"},{"day":2,"utc":"22:04:00","flight":"WN256"},{"day":3,"utc":"23:49:00","flight":"WN115"},{"day":3,"utc":"04:56:00","flight":"WN608"},{"day":3,"utc":"07:06:00","flight":"WN979"},{"day":3,"utc":"17:58:00","flight":"WN156"},{"day":3,"utc":"12:13:00","flight":"WN519"},{"day":4,"utc":"15:37:00","flight":"WN517"},{"day":5,"utc":"12:01:00","flight":"WN179"},{"day":6,"utc":"17:40:00","flight":"WN816"},{"day":6,"utc":"23:40:00","flight":"WN818"},{"day":6,"utc":"04:40:00","flight":"WN055"},{"day":6,"utc":"14:59:00","flight":"WN327"},{"day":6,"utc":"01:10:00","flight":"WN872"}],"distance":578.6157972920432}