{"id":29225,"type":"route","airline":"G4","airlineid":"airline_35","sourceairport":"TYS","destinationairport":"PGD","stops":0,"equipment":"M80","schedule":[{"day":0,"utc":"09:01:00","flight":"G4978"},{"day":0,"utc":"13:26:00","flight":"G4849"},{"day":0,"utc":"18:38:00","flight":"G4233"},{"day":0,"utc":"13:13:00","flight":"G4824"},{"day":0,"utc":"18:46:00","flight":"G4114"},{"day":1,"utc":"06:05:00","flight":"G4393"},{"day":1,"utc":"15:45:00","flight":"G4535"},{"day":1,"utc":"01:56:00","flight":"G4802"},{"day":1,"utc":"15:47:00","flight":"G4095"},{"day":1,"utc":"09:08:00","flight":"G4732"},{"day":2,"utc":"14:06:00","flight":"G4845"},{"day":2,"utc":"05:58:00","flight":"G4217"},{"day":2,"utc":"10:25:00","flight":"G4235"},{"day":2,"utc":"13:25:00","flight":"G4182"},{"day":2,"utc":"00:06:00","flight":"G4939"},{"day":3,"utc":"01:24:00","flight":"G4095"},{"day":3,"utc":"10:59:00","flight":"G4505"},{"day":3,"utc":"22:28:00","flight":"G4539"},{"day":3,"utc":"07:52:00","flight":"G4889"},{"day":3,"utc":"19:02:00","flight":"G4676"},{"day":4,"utc":"18:50:00","flight":"G4602"},{"day":4,"utc":"12:43:00","flight":"G4181"},{"day":4,"utc":"09:37:00","flight":"G4771"},{"day":4,"utc":"16:36:00","flight":"G4670"},{"day":4,"utc":"12:49:00","flight":"G4263"},{"day":5,"utc":"18:18:00","flight":"G4785"},{"day":5,"utc":"13:40:00","flight":"G4552"},{"day":6,"utc":"01:15:00","flight":"G4784"},{"day":6,"utc":"20:56:00","flight":"G4866"},{"day":6,"utc":"02:39:00","flight":"G4581"},{"day":6,"utc":"18:02:00","flight":"G4059"},{"day":6,"utc":"11:32:00","flight":"G4664"}],"distance":1006.7181883417277}