{"id":38525,"type":"route","airline":"LH","airlineid":"airline_3320","sourceairport":"LYS","destinationairport":"MUC","stops":0,"equipment":"E95 CR9","schedule":[{"day":0,"utc":"22:45:00","flight":"LH920"},{"day":0,"utc":"00:26:00","flight":"LH287"},{"day":1,"utc":"17:31:00","flight":"LH640"},{"day":2,"utc":"22:56:00","flight":"LH966"},{"day":2,"utc":"02:18:00","flight":"LH570"},{"day":2,"utc":"20:05:00","flight":"LH174"},{"day":3,"utc":"13:08:00","flight":"LH309"},{"day":3,"utc":"18:25:00","flight":"LH928"},{"day":3,"utc":"12:03:00","flight":"LH525"},{"day":3,"utc":"17:25:00","flight":"LH909"},{"day":4,"utc":"09:47:00","flight":"LH405"},{"day":4,"utc":"00:44:00","flight":"LH291"},{"day":4,"utc":"15:43:00","flight":"LH180"},{"day":4,"utc":"17:19:00","flight":"LH431"},{"day":5,"utc":"06:59:00","flight":"LH545"},{"day":5,"utc":"18:47:00","flight":"LH876"},{"day":6,"utc":"01:20:00","flight":"LH886"},{"day":6,"utc":"00:50:00","flight":"LH270"},{"day":6,"utc":"00:48:00","flight":"LH693"},{"day":6,"utc":"00:08:00","flight":"LH942"}],"distance":585.1506128883901}