{"id":35553,"type":"route","airline":"K5","airlineid":"airline_10765","sourceairport":"MCI","destinationairport":"HRO","stops":0,"equipment":"CNC","schedule":[{"day":0,"utc":"19:35:00","flight":"K5274"},{"day":0,"utc":"13:28:00","flight":"K5918"},{"day":0,"utc":"10:48:00","flight":"K5985"},{"day":1,"utc":"07:28:00","flight":"K5676"},{"day":1,"utc":"11:19:00","flight":"K5818"},{"day":2,"utc":"22:55:00","flight":"K5760"},{"day":2,"utc":"22:11:00","flight":"K5653"},{"day":2,"utc":"13:09:00","flight":"K5259"},{"day":2,"utc":"15:20:00","flight":"K5848"},{"day":3,"utc":"21:31:00","flight":"K5290"},{"day":3,"utc":"04:42:00","flight":"K5541"},{"day":4,"utc":"20:18:00","flight":"K5040"},{"day":5,"utc":"23:50:00","flight":"K5974"},{"day":5,"utc":"07:24:00","flight":"K5347"},{"day":5,"utc":"09:35:00","flight":"K5890"},{"day":5,"utc":"14:18:00","flight":"K5813"},{"day":6,"utc":"10:40:00","flight":"K5797"},{"day":6,"utc":"07:45:00","flight":"K5449"}],"distance":364.32990210764416}