{"id":5248,"type":"route","airline":"AA","airlineid":"airline_24","sourceairport":"DFW","destinationairport":"LEX","stops":0,"equipment":"ERD ER4","schedule":[{"day":0,"utc":"05:02:00","flight":"AA151"},{"day":0,"utc":"15:50:00","flight":"AA343"},{"day":0,"utc":"19:51:00","flight":"AA049"},{"day":1,"utc":"16:10:00","flight":"AA383"},{"day":1,"utc":"16:54:00","flight":"AA174"},{"day":1,"utc":"23:26:00","flight":"AA759"},{"day":1,"utc":"11:00:00","flight":"AA946"},{"day":1,"utc":"05:15:00","flight":"AA386"},{"day":2,"utc":"20:44:00","flight":"AA425"},{"day":2,"utc":"04:16:00","flight":"AA283"},{"day":2,"utc":"13:47:00","flight":"AA202"},{"day":2,"utc":"11:31:00","flight":"AA024"},{"day":3,"utc":"18:45:00","flight":"AA327"},{"day":3,"utc":"11:46:00","flight":"AA459"},{"day":3,"utc":"04:25:00","flight":"AA559"},{"day":3,"utc":"05:32:00","flight":"AA739"},{"day":4,"utc":"10:24:00","flight":"AA214"},{"day":4,"utc":"16:36:00","flight":"AA094"},{"day":4,"utc":"10:41:00","flight":"AA755"},{"day":5,"utc":"18:42:00","flight":"AA941"},{"day":5,"utc":"13:36:00","flight":"AA059"},{"day":5,"utc":"06:27:00","flight":"AA980"},{"day":5,"utc":"17:35:00","flight":"AA189"},{"day":6,"utc":"19:50:00","flight":"AA788"},{"day":6,"utc":"15:10:00","flight":"AA325"},{"day":6,"utc":"03:28:00","flight":"AA339"},{"day":6,"utc":"03:07:00","flight":"AA129"}],"distance":1261.1191306498124}